ainlp/__init__.py
ainlp/collector.py
ainlp/metrics.py
ainlp/text_utils.py
ainlp/tokenizer.py
ainlp/transformers_utils.py
ainlp-0.1.6.dist-info/LICENSE
ainlp-0.1.6.dist-info/METADATA
ainlp-0.1.6.dist-info/WHEEL
ainlp-0.1.6.dist-info/top_level.txt
ainlp-0.1.6.dist-info/RECORD
