Metadata-Version: 2.1
Name: ainlp
Version: 0.1.6
Summary: nlp library which support text processing methods, text match methods, etc.
Home-page: UNKNOWN
Author: ymai
Author-email: zhangjinjie@yimian.com.cn
License: UNKNOWN
Platform: UNKNOWN
Classifier: Programming Language :: Python :: 3
Classifier: License :: OSI Approved :: MIT License
Classifier: Operating System :: OS Independent
Requires-Python: >=3.6
Requires-Dist: pymysql
Requires-Dist: emoji
Requires-Dist: jieba
Requires-Dist: pyrefo
Requires-Dist: attrdict
Requires-Dist: tqdm
